pycallshot/__init__.py
pycallshot/dice_tower.py
pycallshot/roll.py
pycallshot-0.1.1.dist-info/LICENSE
pycallshot-0.1.1.dist-info/METADATA
pycallshot-0.1.1.dist-info/WHEEL
pycallshot-0.1.1.dist-info/top_level.txt
pycallshot-0.1.1.dist-info/RECORD
