Metadata-Version: 2.1
Name: pycallshot
Version: 0.1.1
Summary: A simple independent library for rolling dice and managing dice rolls
Home-page: https://github.com/dmitry-helios/pycallshot
Author: Dmitry Helios
License: MIT License
Project-URL: Homepage, https://github.com/dmitry-helios/pycallshot
Keywords: dice,rpg,game,random
Classifier: License :: OSI Approved :: MIT License
Classifier: Programming Language :: Python
Classifier: Programming Language :: Python :: 3
Requires-Python: >=3.7
License-File: LICENSE
